jgtfxcon/FXCONHelperTransact.py
jgtfxcon/FXHelperTransact.py
jgtfxcon/FXTradeStopValidator.py
jgtfxcon/FXTransact.py
jgtfxcon/JGTCloudFS.py
jgtfxcon/JGTConfig.py
jgtfxcon/JGTCore.py
jgtfxcon/JGTImage.py
jgtfxcon/JGTLoader.py
jgtfxcon/JGTPDHelper.py
jgtfxcon/JGTPDS.py
jgtfxcon/JGTPDS.test.py
jgtfxcon/JGTPDSSvc.py
jgtfxcon/__init__.py
jgtfxcon/__main__.py
jgtfxcon/dkfxcli.py
jgtfxcon/dl_properties.py
jgtfxcon/fsserver.py
jgtfxcon/fxchgstop.py
jgtfxcon/fxclosebyinstrument.py
jgtfxcon/fxdevclose_lots.py
jgtfxcon/fxdkcli.py
jgtfxcon/fxsetsubscription.py
jgtfxcon/iprops.py
jgtfxcon/jgt2312.py
jgtfxcon/jgtbtetl1.py
jgtfxcon/jgtbtetl2.py
jgtfxcon/jgtdotenv.py
jgtfxcon/jgtetl.py
jgtfxcon/jgtflags.py
jgtfxcon/jgtfxc.py
jgtfxcon/jgtfxc.test.py
jgtfxcon/jgtfxcli.py
jgtfxcon/jgtfxcliw.py
jgtfxcon/jgtfxcommon.py
jgtfxcon/jgtfxentryorder.py
jgtfxcon/jgtfxhelper.py
jgtfxcon/jgtfxremoveorder.py
jgtfxcon/jgtfxreport.py
jgtfxcon/jgtfxtransact.py
jgtfxcon/pdsserver.py
jgtfxcon/pto_fxreport_xls2csv_tables.py
jgtfxcon/svcLiveChartDataExport.py
jgtfxcon/svcLiveChartDataExport_config_generator.py
jgtfxcon/test_JGTPDS.py
jgtfxcon/test_jgtfxc.py
jgtfxcon/tstcli_jgtfxcli_with_settings.py
jgtfxcon/wsl-run-command.py
jgtfxcon/common_samples/BatchOrderMonitor.py
jgtfxcon/common_samples/OrderMonitor.py
jgtfxcon/common_samples/OrderMonitorNetting.py
jgtfxcon/common_samples/TableListenerContainer.py
jgtfxcon/common_samples/__init__.py
jgtfxcon/common_samples/common.py
jgtfxcon/forexconnect/EachRowListener.py
jgtfxcon/forexconnect/ForexConnect.py
jgtfxcon/forexconnect/LiveHistory.py
jgtfxcon/forexconnect/ResponseListener.py
jgtfxcon/forexconnect/SessionStatusListener.py
jgtfxcon/forexconnect/TableListener.py
jgtfxcon/forexconnect/TableManagerListener.py
jgtfxcon/forexconnect/__init__.py
jgtfxcon/forexconnect/common.py
jgtfxcon/forexconnect/errors.py
jgtfxcon/forexconnect/x-pyd.py
jgtfxcon/forexconnect/lib/linux/__init__.py
jgtfxcon/forexconnect/lib/linux/fxcorepy.so
jgtfxcon-0.6.125.dist-info/LICENSE
jgtfxcon-0.6.125.dist-info/METADATA
jgtfxcon-0.6.125.dist-info/WHEEL
jgtfxcon-0.6.125.dist-info/entry_points.txt
jgtfxcon-0.6.125.dist-info/top_level.txt
jgtfxcon-0.6.125.dist-info/RECORD
