Metadata-Version: 2.1
Name: jgtfxcon
Version: 0.6.125
Summary: PDS Services
Home-page: https://github.com/jgwill/jgtfxcon
Author: GUillaume Isabelle
Author-email: Guillaume Isabelle <jgi@jgwill.com>
Project-URL: Homepage, https://github.com/jgwill/jgtfxcon
Project-URL: Bug Tracker, https://github.com/jgwill/jgtfxcon/issues
Classifier: Programming Language :: Python :: 3
Classifier: License :: OSI Approved :: MIT License
Classifier: Operating System :: OS Independent
Requires-Python: >=3.7
License-File: LICENSE
Requires-Dist: pandas >=0.25.1
Requires-Dist: python-dotenv >=0.19.2
Requires-Dist: jgtutils >=0.2.218
Requires-Dist: jgtfx2console >=0.5.15
Requires-Dist: tlid
Requires-Dist: flask
Requires-Dist: openpyxl
Provides-Extra: dev
Requires-Dist: flake8 <3.7.0,>=3.6.0 ; extra == 'dev'
Requires-Dist: isort <4.4.0,>=4.3.4 ; extra == 'dev'
Requires-Dist: coverage ; extra == 'dev'
Requires-Dist: pytest >=3.10 ; extra == 'dev'
Requires-Dist: readme-renderer ; extra == 'dev'
Requires-Dist: sphinx ; extra == 'dev'
Requires-Dist: sphinx-rtd-theme >=0.4.0 ; extra == 'dev'
Provides-Extra: dev-docs
Requires-Dist: readme-renderer ; extra == 'dev-docs'
Requires-Dist: sphinx ; extra == 'dev-docs'
Requires-Dist: sphinx-rtd-theme >=0.4.0 ; extra == 'dev-docs'
Provides-Extra: dev-lint
Requires-Dist: flake8 <3.7.0,>=3.6.0 ; extra == 'dev-lint'
Requires-Dist: isort <4.4.0,>=4.3.4 ; extra == 'dev-lint'
Provides-Extra: dev-test
Requires-Dist: coverage ; extra == 'dev-test'
Requires-Dist: pytest >=3.10 ; extra == 'dev-test'
